{
  "reports": [
    {
      "id": "rpt-003",
      "title": "تعطیلی رواق کشوردوست و اعتراضات در حرم امام رضا (ع)",
      "summary": "تحلیل بازتاب رسانه‌ای تعطیلی رواق کشوردوست، تحصن معترضان، حضور کفن‌پوشان مشهدی و واکنش‌های روحانیت و کاربران در ۳ روز گذشته.",
      "category": "فرهنگ و هنر",
      "category_icon": "🕌",
      "date": "۳ تیر ۱۴۰۵",
      "date_gregorian": "2026-06-24",
      "keywords": ["تحصن", "کشوردوست", "رواق کشوردوست", "کفن پوش مشهدی", "حرم امام رضا", "آستان قدس", "مشهد"],
      "hashtags": ["#رواق_کشوردوست", "#حرم_امام_رضا", "#تحصن", "#کفن_پوشان"],
      "platforms": ["Telegram", "X", "Instagram"],
      "file": "reports/1405-04-03-keshvar-doust-rowaq.html",
      "views": 0,
      "featured": true,
      "sentiment": {
        "positive": 12,
        "neutral": 18,
        "negative": 70
      },
      "total_content": 15000
    },
    {
      "id": "rpt-002",
      "title": "اولین دور مذاکرات چهارجانبه ایران و آمریکا در سوئیس",
      "summary": "تحلیل بازتاب رسانه‌ای مذاکرات بورگن‌اشتوک با حضور قالیباف و ونس، بیانیه مشترک، نقشه راه ۶۰ روزه و تهدیدات همزمان ترامپ درباره تنگه هرمز.",
      "category": "سیاست",
      "category_icon": "🏛️",
      "date": "۳ تیر ۱۴۰۵",
      "date_gregorian": "2026-06-24",
      "keywords": ["مذاکرات", "قالیباف", "عراقچی", "ونز", "ترامپ", "تنگه هرمز", "بیانیه مشترک", "بورگن‌اشتوک"],
      "hashtags": ["#مذاکرات_ایران_و_آمریکا", "#بورگن_اشتوک", "#قالیباف", "#تنگه_هرمز"],
      "platforms": ["X", "Telegram", "Instagram"],
      "file": "reports/1405-04-03-iran-us-talks.html",
      "views": 0,
      "featured": true,
      "sentiment": {
        "positive": 42,
        "neutral": 25,
        "negative": 33
      },
      "total_content": 20000
    },
    {
      "id": "rpt-001",
      "title": "حضور تیم ملی ایران در جام جهانی ۲۰۲۶ — گزارش روز ۵",
      "summary": "تحلیل کامل بازتاب رسانه‌ای بازی ایران و بلژیک، درخشش بیرانوند، مناقشه پرچم و مصاحبه جنجالی طارمی در رسانه‌های داخلی و بین‌المللی.",
      "category": "ورزش",
      "category_icon": "⚽",
      "date": "۲ تیر ۱۴۰۵",
      "date_gregorian": "2026-06-23",
      "keywords": ["تیم ملی", "بیرانوند", "جام جهانی", "طارمی", "پرچم"],
      "hashtags": ["#تیم_ملی_ایران", "#بیرانوند", "#جام_جهانی_۲۰۲۶"],
      "platforms": ["Instagram", "X", "YouTube", "TikTok", "Telegram"],
      "file": "reports/1405-04-02-iran-world-cup.html",
      "views": 0,
      "featured": true,
      "sentiment": {
        "positive": 48,
        "neutral": 22,
        "negative": 30
      },
      "total_content": 12900
    }
  ],
  "metadata": {
    "last_updated": "2026-06-24T18:00:00Z",
    "version": "1.0"
  }
}
